{
  "filename": "Article",
  "en": {
    "title": "Translation Test",
    "subtitle": "Date Published: {{date}}",
    "plutest": "First, lets look at pluralization. {{count}} item.",
    "plutest_plural": "First, lets look at pluralization. {{count}} items."
  },
  "de": {
    "title": "Übersetzungstest",
    "subtitle": "Veröffentlichungsdatum: {{date}}",
    "plutest": "Betrachten wir zunächst die Pluralisierung. {{count}} Gegenstand",
    "plutest_plural": "Betrachten wir zunächst die Pluralisierung. {{count}} Gegenstände"
  }
}